pyramid_hypernova/__init__.py
pyramid_hypernova/batch.py
pyramid_hypernova/plugins.py
pyramid_hypernova/rendering.py
pyramid_hypernova/request.py
pyramid_hypernova/token_replacement.py
pyramid_hypernova/tweens.py
pyramid_hypernova/types.py
pyramid_hypernova-10.0.2.dist-info/LICENSE
pyramid_hypernova-10.0.2.dist-info/METADATA
pyramid_hypernova-10.0.2.dist-info/WHEEL
pyramid_hypernova-10.0.2.dist-info/top_level.txt
pyramid_hypernova-10.0.2.dist-info/RECORD
