Metadata-Version: 2.1
Name: pyramid-hypernova
Version: 10.0.2
Summary: A Python client for Airbnb's Hypernova server, for use with the Pyramid web framework.
Home-page: https://github.com/Yelp/pyramid-hypernova
Author: Yelp, Inc.
Author-email: opensource+pyramid-hypernova@yelp.com
License: MIT
Classifier: Programming Language :: Python :: 3
Classifier: Programming Language :: Python :: 3.10
Classifier: License :: OSI Approved :: MIT License
Requires-Python: >=3.10
License-File: LICENSE
Requires-Dist: fido
Requires-Dist: more-itertools
Requires-Dist: requests
